robust_laplacian_bindings.cpython-37m-i386-linux-gnu.so
robust_laplacian-1.0.0.dist-info/RECORD
robust_laplacian-1.0.0.dist-info/METADATA
robust_laplacian-1.0.0.dist-info/WHEEL
robust_laplacian-1.0.0.dist-info/licenses/LICENSE
lib/libgeometry-central.a
robust_laplacian/__init__.py
robust_laplacian/core.py
