Metadata-Version: 2.1
Name: robust_laplacian
Version: 1.0.0
Summary: Robust Laplace matrices for meshes and point clouds
Author-Email: Nicholas Sharp <nmwsharp@gmail.com>
Maintainer-Email: Nicholas Sharp <nmwsharp@gmail.com>
License: MIT License
Classifier: Development Status :: 5 - Production/Stable
Classifier: License :: OSI Approved :: MIT License
Classifier: Programming Language :: Python :: 3
Project-URL: Homepage, https://github.com/nmwsharp/robust-laplacians-py
Requires-Python: >=3.7
Requires-Dist: numpy
